LICENSE
MANIFEST.in
Makefile
README.mkd
README.rst
requirements.txt
setup.py
Rhino.egg-info/PKG-INFO
Rhino.egg-info/SOURCES.txt
Rhino.egg-info/dependency_links.txt
Rhino.egg-info/top_level.txt
examples/__init__.py
examples/build_url.py
examples/conneg.py
examples/content_type_versioning.py
examples/helloworld.py
examples/json_api.py
examples/movie_db/__init__.py
examples/movie_db/model.py
examples/movie_db/web.py
examples/movie_db/static/favicon.ico
examples/movie_db/static/style.css
examples/movie_db/templates/actor.html
examples/movie_db/templates/base.html
examples/movie_db/templates/index.html
examples/movie_db/templates/movie.html
examples/nested_mappers/__init__.py
examples/nested_mappers/main.py
examples/nested_mappers/pages.py
examples/nested_mappers/users.py
examples/tutorial/__init__.py
examples/tutorial/model.py
examples/tutorial/service.py
examples/tutorial/todo_app.py
examples/tutorial/static/style.css
examples/tutorial/templates/base.html
examples/tutorial/templates/delete_todo.html
examples/tutorial/templates/edit_todo.html
examples/tutorial/templates/index.html
examples/wiki/README
examples/wiki/__init__.py
examples/wiki/requirements.txt
examples/wiki/storage.py
examples/wiki/wiki.py
rhino/__init__.py
rhino/errors.py
rhino/http.py
rhino/mapper.py
rhino/request.py
rhino/resource.py
rhino/response.py
rhino/static.py
rhino/test.py
rhino/urls.py
rhino/util.py
rhino/ext/__init__.py
rhino/ext/jinja2.py
rhino/ext/session.py
rhino/ext/sqlalchemy.py
rhino/vendor/__init__.py
rhino/vendor/mimeparse.py
test/test_callbacks.py
test/test_context.py
test/test_http.py
test/test_mapper.py
test/test_representations.py
test/test_request.py
test/test_resource.py
test/test_resourcewrapper.py
test/test_response.py
test/test_route.py
test/test_static.py
test/test_urls.py
test/test_util.py
test/test_wrapper.py
test/examples/test_build_url.py
test/examples/test_conneg.py
test/examples/test_content_type_versioning.py
test/examples/test_helloworld.py
test/examples/test_json_api.py
test/examples/test_movie_db.py
test/examples/test_nested_mappers.py
test/examples/test_wiki.py
