Metadata-Version: 1.1
Name: Rhino
Version: 0.0.5
Summary: A microframework for building RESTful web services
Home-page: https://github.com/trendels/rhino
Author: Stanis Trendelenburg
Author-email: stanis.trendelenburg@gmail.com
License: MIT
Platform: UNKNOWN
Classifier: License :: OSI Approved :: MIT License
Classifier: Programming Language :: Python
Classifier: Programming Language :: Python :: 2
Classifier: Programming Language :: Python :: 2.6
Classifier: Programming Language :: Python :: 2.7
